evalx/__init__.py
evalx/cli.py
evalx/agents/interpreter/__init__.py
evalx/agents/orchestrator/__init__.py
evalx/agents/planner/__init__.py
evalx/core/base.py
evalx/core/suite.py
evalx/core/types.py
evalx/meta_evaluation/__init__.py
evalx/metrics/hybrid/__init__.py
evalx/metrics/llm_judge/__init__.py
evalx/metrics/llm_judge/base.py
evalx/metrics/llm_judge/models.py
evalx/metrics/llm_judge/prompts.py
evalx/metrics/llm_judge/structured_output.py
evalx/metrics/multimodal/__init__.py
evalx/metrics/traditional/__init__.py
evalx/metrics/traditional/bert_score.py
evalx/metrics/traditional/bleu.py
evalx/metrics/traditional/exact_match.py
evalx/metrics/traditional/levenshtein.py
evalx/metrics/traditional/meteor.py
evalx/metrics/traditional/rouge.py
evalx/metrics/traditional/semantic_similarity.py
evalx/utils/async_utils.py
evalx/utils/cache.py
evalx/utils/config.py
evalx/validation/benchmarks/__init__.py
evalx/validation/human/__init__.py
evalx/validation/statistical/__init__.py
evalx-0.1.0.dist-info/METADATA
evalx-0.1.0.dist-info/WHEEL
evalx-0.1.0.dist-info/entry_points.txt
evalx-0.1.0.dist-info/top_level.txt
evalx-0.1.0.dist-info/RECORD
