Metadata-Version: 2.4
Name: evalx
Version: 0.1.0
Summary: Next-generation evaluation framework for LLM applications with research-grade validation and production-ready performance
Home-page: https://github.com/vishalseelam/EvalX
Author: Vishal Seelam
Author-email: Vishal Seelam <vishalseelam@gmail.com>
License: MIT
Project-URL: Homepage, https://github.com/vishalseelam/EvalX
Project-URL: Documentation, https://github.com/vishalseelam/EvalX
Project-URL: Repository, https://github.com/vishalseelam/EvalX
Project-URL: Issues, https://github.com/vishalseelam/EvalX/issues
Keywords: llm,evaluation,metrics,ai,nlp,machine-learning
Classifier: Development Status :: 4 - Beta
Classifier: Intended Audience :: Developers
Classifier: Intended Audience :: Science/Research
Classifier: License :: OSI Approved :: MIT License
Classifier: Programming Language :: Python :: 3
Classifier: Programming Language :: Python :: 3.9
Classifier: Programming Language :: Python :: 3.10
Classifier: Programming Language :: Python :: 3.11
Classifier: Programming Language :: Python :: 3.12
Classifier: Topic :: Scientific/Engineering :: Artificial Intelligence
Classifier: Topic :: Software Development :: Libraries :: Python Modules
Requires-Python: >=3.9
Requires-Dist: numpy<2.0.0,>=1.21.0
Requires-Dist: pandas<3.0.0,>=1.3.0
Requires-Dist: scipy<2.0.0,>=1.7.0
Requires-Dist: scikit-learn<2.0.0,>=1.0.0
Requires-Dist: transformers<5.0.0,>=4.20.0
Requires-Dist: sentence-transformers<3.0.0,>=2.2.0
Requires-Dist: torch<3.0.0,>=1.12.0
Requires-Dist: nltk<4.0.0,>=3.7
Requires-Dist: spacy<4.0.0,>=3.4.0
Requires-Dist: rouge-score<1.0.0,>=0.1.0
Requires-Dist: bert-score<1.0.0,>=0.3.0
Requires-Dist: openai<2.0.0,>=1.0.0
Requires-Dist: anthropic<1.0.0,>=0.3.0
Requires-Dist: langchain<1.0.0,>=0.1.0
Requires-Dist: langchain-openai<1.0.0,>=0.1.0
Requires-Dist: langchain-anthropic<1.0.0,>=0.1.0
Requires-Dist: langsmith<1.0.0,>=0.1.0
Requires-Dist: aiohttp<4.0.0,>=3.8.0
Requires-Dist: tenacity<9.0.0,>=8.0.0
Requires-Dist: statsmodels<1.0.0,>=0.13.0
Requires-Dist: matplotlib<4.0.0,>=3.5.0
Requires-Dist: seaborn<1.0.0,>=0.11.0
Requires-Dist: plotly<6.0.0,>=5.0.0
Requires-Dist: pydantic<3.0.0,>=2.0.0
Requires-Dist: typer<1.0.0,>=0.9.0
Requires-Dist: rich<14.0.0,>=13.0.0
Requires-Dist: tqdm<5.0.0,>=4.64.0
Requires-Dist: python-dotenv<2.0.0,>=1.0.0
Requires-Dist: pyyaml<7.0,>=6.0
Requires-Dist: jsonschema<5.0.0,>=4.0.0
Requires-Dist: pillow<11.0.0,>=9.0.0
Requires-Dist: opencv-python<5.0.0,>=4.5.0
Requires-Dist: librosa<1.0.0,>=0.9.0
Requires-Dist: datasets<3.0.0,>=2.0.0
Requires-Dist: evaluate<1.0.0,>=0.4.0
Provides-Extra: dev
Requires-Dist: pytest<8.0.0,>=7.0.0; extra == "dev"
Requires-Dist: pytest-asyncio<1.0.0,>=0.21.0; extra == "dev"
Requires-Dist: pytest-cov<5.0.0,>=4.0.0; extra == "dev"
Requires-Dist: black<25.0.0,>=22.0.0; extra == "dev"
Requires-Dist: isort<6.0.0,>=5.10.0; extra == "dev"
Requires-Dist: flake8<8.0.0,>=5.0.0; extra == "dev"
Requires-Dist: mypy<2.0.0,>=1.0.0; extra == "dev"
Requires-Dist: pre-commit<4.0.0,>=2.20.0; extra == "dev"
Provides-Extra: research
Requires-Dist: jupyter<2.0.0,>=1.0.0; extra == "research"
Requires-Dist: ipywidgets<9.0.0,>=8.0.0; extra == "research"
Requires-Dist: datasets<3.0.0,>=2.0.0; extra == "research"
Requires-Dist: wandb<1.0.0,>=0.13.0; extra == "research"
Requires-Dist: mlflow<3.0.0,>=2.0.0; extra == "research"
Provides-Extra: production
Requires-Dist: redis<6.0.0,>=4.0.0; extra == "production"
Requires-Dist: celery<6.0.0,>=5.2.0; extra == "production"
Requires-Dist: prometheus-client<1.0.0,>=0.15.0; extra == "production"
Requires-Dist: sentry-sdk<2.0.0,>=1.0.0; extra == "production"
Provides-Extra: all
Requires-Dist: evalx[dev,production,research]; extra == "all"
Dynamic: author
Dynamic: home-page
Dynamic: requires-python
